GenomeVisualizer/__init__.py
GenomeVisualizer/basic.py
GenomeVisualizer/motifs.py
GenomeVisualizer/replication.py
GenomeVisualizer/visualization.py
genomevisualizer-0.0.2.dist-info/licenses/LICENSE
genomevisualizer-0.0.2.dist-info/METADATA
genomevisualizer-0.0.2.dist-info/WHEEL
genomevisualizer-0.0.2.dist-info/top_level.txt
genomevisualizer-0.0.2.dist-info/RECORD
