Metadata-Version: 2.4
Name: GenomeVisualizer
Version: 0.0.2
Summary: A toolbox for detecting DNA replication origins and regulatory motifs in genomic sequences
Author: Varga Henrietta
Maintainer-email: Varga Henrietta <varga.henrietta.julianna@hallgato.ppke.hu>
Project-URL: Homepage, https://github.com/vargaheni05/GenomeVisualizer
Project-URL: Documentation, https://genomevisualizer.readthedocs.io/en/latest/
Project-URL: Repository, https://github.com/vargaheni05/GenomeVisualizer.git
Project-URL: Issues, https://github.com/vargaheni05/GenomeVisualizer/issues
Classifier: Development Status :: 3 - Alpha
Classifier: Programming Language :: Python :: 3.12
Classifier: License :: OSI Approved :: GNU General Public License v3 (GPLv3)
Classifier: Operating System :: OS Independent
Classifier: Topic :: Scientific/Engineering
Requires-Python: >=3.10
License-File: LICENSE
Requires-Dist: matplotlib>=3.9.2
Requires-Dist: numpy>=1.25.2
Requires-Dist: pandas>=2.2.2
Requires-Dist: logomaker>=0.8
Dynamic: license-file
